examples/__init__.py
examples/predict_stock_price.py
keras_generators/__init__.py
keras_generators/callbacks.py
keras_generators/common.py
keras_generators/encoders.py
keras_generators/generators.py
keras_generators/splitters.py
keras_generators/model_abstractions/__init__.py
keras_generators/model_abstractions/model_object.py
keras_generators/model_abstractions/model_params.py
keras_generators-1.4.5.dist-info/LICENSE
keras_generators-1.4.5.dist-info/METADATA
keras_generators-1.4.5.dist-info/WHEEL
keras_generators-1.4.5.dist-info/top_level.txt
keras_generators-1.4.5.dist-info/RECORD
