Metadata-Version: 2.1
Name: keras-generators
Version: 1.4.5
Summary: Multi-dimensional/Multi-input/Multi-output Data preprocessing and Batch Generators for Keras models
Home-page: https://github.com/asuiu/keras-generators
Author: Andrei Suiu
Author-email: andrei.suiu@gmail.com
License: Apache License 2.0
Keywords: ML,DataGenerators,Keras,tensorflow
Classifier: Intended Audience :: Developers
Classifier: Intended Audience :: Education
Classifier: Intended Audience :: Science/Research
Classifier: License :: OSI Approved :: Apache Software License
Classifier: Programming Language :: Python :: 3.10
Classifier: Programming Language :: Python :: 3.11
Classifier: Programming Language :: Python :: 3.12
Classifier: Topic :: Scientific/Engineering :: Mathematics
Classifier: Topic :: Software Development :: Libraries :: Python Modules
Classifier: Topic :: Software Development :: Libraries
Requires-Python: >=3.10
License-File: LICENSE
Requires-Dist: dill >=0.3.8
Requires-Dist: numpy >=1.20
Requires-Dist: pip >=22.1.2
Requires-Dist: pydantic >=2.0
Requires-Dist: pyxtension >=1.15.0
Requires-Dist: scikit-learn >=0.22.2
Requires-Dist: setuptools >=63.4.1
Requires-Dist: tensorflow >=2.16
Requires-Dist: tf-keras >=2.16.0
Requires-Dist: tsx >=0.1.1
Requires-Dist: wheel >=0.37.1
Provides-Extra: tests
